CHANGES.md
LICENSE.txt
MANIFEST.in
README.md
setup.py
lib/sources.py
lib/sources.egg-info/PKG-INFO
lib/sources.egg-info/SOURCES.txt
lib/sources.egg-info/dependency_links.txt
lib/sources.egg-info/entry_points.txt
lib/sources.egg-info/not-zip-safe
lib/sources.egg-info/top_level.txt