Metadata-Version: 1.0
Name: sources
Version: 1.0.1
Summary: a command-line script for getting/updating source dirs from a config file giving SCC URLs
Home-page: http://github.com/trentm/sources
Author: Trent Mick
Author-email: trentm@gmail.com
License: MIT
Keywords: sources scc git hg subversion svn
Platform: UNKNOWN
Classifier: Development Status :: 5 - Production/Stable
Classifier: Environment :: Console
Classifier: Intended Audience :: Developers
Classifier: License :: OSI Approved :: MIT License
Classifier: Operating System :: OS Independent
Classifier: Programming Language :: Python :: 2
Classifier: Programming Language :: Python :: 2.5
Classifier: Programming Language :: Python :: 2.6
Classifier: Programming Language :: Python :: 2.7
Classifier: Programming Language :: Python :: 3
Classifier: Programming Language :: Python :: 3.1
Classifier: Topic :: Software Development :: Libraries :: Python Modules
